{
    "version": "1.3.12",
    "description": "AriaNg, a modern web frontend making aria2 easier to use.",
    "homepage": "https://github.com/mayswind/AriaNg",
    "license": "MIT",
    "url": "https://github.com/mayswind/AriaNg/releases/download/1.3.12/AriaNg-1.3.12-AllInOne.zip",
    "hash": "fe5538f9a7bb3f78a455133e5c46bfa2c6a45e21f272ae3a4d5749903dd151d0",
    "shortcuts": [
        [
            "index.html",
            "AriaNg"
        ]
    ],
    "checkver": {
        "github": "https://github.com/mayswind/AriaNg"
    },
    "autoupdate": {
        "url": "https://github.com/mayswind/AriaNg/releases/download/$version/AriaNg-$version-AllInOne.zip"
    }
}
